{"@context":"http://iiif.io/api/presentation/3/context.json","id":"https://vintagereality.projektemacher.org/collection.json","items":[{"id":"https://vintagereality.projektemacher.org/post/florida/manifest.json","label":{"de":["Wie Kokospalmen im Sande von Florida gedeihen. V. St. v. N.-A."]},"thumbnail":[{"format":"image/jpeg","height":150,"id":"https://vintagereality.projektemacher.org/post/florida/front/full/full/0/default_hu_3642fff4312d1eb3.jpg","type":"Image","width":300},{"format":"image/jpeg","height":2107,"id":"https://vintagereality.projektemacher.org/post/florida/front/full/full/0/default.jpg","service":[{"id":"https://vintagereality.projektemacher.org/post/florida/front","profile":"level0","type":"ImageService2"}],"type":"Image","width":4224}],"type":"Manifest"}],"label":{"de":["Vintage Reality"]},"type":"Collection"}